spoke/__init__.py
spoke/cli.py
spoke/genid.py
spoke/simple.py
spoke/version.py
spoke/wait.py
spoke/conn/__init__.py
spoke/conn/abc.py
spoke/conn/pack.py
spoke/conn/socket.py
spoke/pubsub/__init__.py
spoke/pubsub/client.py
spoke/pubsub/error.py
spoke/pubsub/pack.py
spoke/pubsub/proxy.py
spoke/pubsub/route.py
spoke/pubsub/server.py
pyspoke-1.1.2.dist-info/LICENSE
pyspoke-1.1.2.dist-info/METADATA
pyspoke-1.1.2.dist-info/WHEEL
pyspoke-1.1.2.dist-info/entry_points.txt
pyspoke-1.1.2.dist-info/top_level.txt
pyspoke-1.1.2.dist-info/RECORD
