Metadata-Version: 2.1
Name: pyspoke
Version: 1.1.2
Summary: A publish/subscribe and rpc library in python
Home-page: https://gitlab.com/samflam/pyspoke
Author: samflam
Author-email: pyspoke@samflam.com
Classifier: Programming Language :: Python :: 3
Classifier: License :: OSI Approved :: MIT License
Classifier: Operating System :: POSIX :: Linux
Requires-Python: >=3.7
License-File: LICENSE
